{"blog": [1, "/categories/blog/", {"posts": [{"date": "03/30/2012", "isodate": "2012-03-30T23:00:00-03:00", "title": "Welcome to Nikola", "url": "/posts/welcome-to-nikola/"}]}], "ci": [1, "/categories/ci/", {"posts": [{"date": "02/06/2016", "isodate": "2016-02-06T17:00:00-09:00", "title": "\u30ab\u30d0\u30ec\u30c3\u30b8\u53d6\u5f97\u30b5\u30fc\u30d3\u30b9\u306e\u6bd4\u8f03\uff08Coveralls.io\u3068Codecove.io)", "url": "/posts/ci/"}]}], "demo": [1, "/categories/demo/", {"posts": [{"date": "03/30/2012", "isodate": "2012-03-30T23:00:00-03:00", "title": "Welcome to Nikola", "url": "/posts/welcome-to-nikola/"}, {"date": "03/30/2012", "isodate": "2012-03-30T23:00:00-03:00", "title": "Bootstrap Demo", "url": "/stories/bootstrap-demo/"}]}], "nikola": [1, "/categories/nikola/", {"posts": [{"date": "03/30/2012", "isodate": "2012-03-30T23:00:00-03:00", "title": "Welcome to Nikola", "url": "/posts/welcome-to-nikola/"}]}], "python": [4, "/categories/python/", {"posts": [{"date": "02/14/2016", "isodate": "2016-02-14T13:00:00+09:00", "title": "Livemark.vim\u3092\u8272\u3005\u66f4\u65b0\u3057\u307e\u3057\u305f", "url": "/posts/livemark_update/"}, {"date": "02/06/2016", "isodate": "2016-02-06T17:00:00-09:00", "title": "\u30ab\u30d0\u30ec\u30c3\u30b8\u53d6\u5f97\u30b5\u30fc\u30d3\u30b9\u306e\u6bd4\u8f03\uff08Coveralls.io\u3068Codecove.io)", "url": "/posts/ci/"}, {"date": "01/29/2016", "isodate": "2016-01-29T10:00:00+09:00", "title": "Vim \u306b channel \u304c\u5b9f\u88c5\u3055\u308c\u305f\u306e\u3067 Markdown \u3092\u30d7\u30ec\u30d3\u30e5\u30fc\u3059\u308b\u30d7\u30e9\u30b0\u30a4\u30f3\u3092\u4f5c\u308a\u307e\u3057\u305f", "url": "/posts/livemark/"}, {"date": "03/30/2012", "isodate": "2012-03-30T23:00:00-03:00", "title": "Welcome to Nikola", "url": "/posts/welcome-to-nikola/"}]}], "vim": [3, "/categories/vim/", {"posts": [{"date": "02/14/2016", "isodate": "2016-02-14T13:00:00+09:00", "title": "Livemark.vim\u3092\u8272\u3005\u66f4\u65b0\u3057\u307e\u3057\u305f", "url": "/posts/livemark_update/"}, {"date": "02/06/2016", "isodate": "2016-02-06T10:00:00+09:00", "title": "Vim \u306e channel \u3068 json \u306e\u30d1\u30d5\u30a9\u30fc\u30de\u30f3\u30b9", "url": "/posts/channel/"}, {"date": "01/29/2016", "isodate": "2016-01-29T10:00:00+09:00", "title": "Vim \u306b channel \u304c\u5b9f\u88c5\u3055\u308c\u305f\u306e\u3067 Markdown \u3092\u30d7\u30ec\u30d3\u30e5\u30fc\u3059\u308b\u30d7\u30e9\u30b0\u30a4\u30f3\u3092\u4f5c\u308a\u307e\u3057\u305f", "url": "/posts/livemark/"}]}]}